custom_tail/__init__.py
custom_tail/main.py
custom_tail_cli-0.1.0.dist-info/METADATA
custom_tail_cli-0.1.0.dist-info/WHEEL
custom_tail_cli-0.1.0.dist-info/entry_points.txt
custom_tail_cli-0.1.0.dist-info/top_level.txt
custom_tail_cli-0.1.0.dist-info/RECORD
